hoardy/__init__.py
hoardy/__main__.py
hoardy-0.2.0.dist-info/COPYING
hoardy-0.2.0.dist-info/COPYING.LESSER
hoardy-0.2.0.dist-info/METADATA
hoardy-0.2.0.dist-info/WHEEL
hoardy-0.2.0.dist-info/entry_points.txt
hoardy-0.2.0.dist-info/top_level.txt
hoardy-0.2.0.dist-info/RECORD
