Metadata-Version: 2.2
Name: hoardy
Version: 0.2.0
Summary: Find files matching given criteria quickly, find duplicated files and deduplicate them, record file hashes and verify them, etc.
Author-email: Jan Malakhovski <oxij@oxij.org>
License: LGPL-3.0-or-later
Project-URL: Homepage, https://oxij.org/software/hoardy/
Project-URL: GitHub, https://github.com/Own-Data-Privateer/hoardy
Project-URL: Support Development, https://oxij.org/#support
Keywords: backup,archive,hoard,search,deduplicate
Classifier: Development Status :: 4 - Beta
Classifier: Programming Language :: Python :: 3
Classifier: License :: OSI Approved :: GNU Lesser General Public License v3 or later (LGPLv3+)
Classifier: Intended Audience :: End Users/Desktop
Classifier: Topic :: System :: Archiving
Classifier: Topic :: System :: Archiving :: Backup
Classifier: Topic :: System :: Archiving :: Compression
Classifier: Topic :: System :: Archiving :: Mirroring
Classifier: Topic :: System :: Recovery Tools
Classifier: Operating System :: POSIX
Classifier: Environment :: Console
Requires-Python: >=3.11
License-File: COPYING
License-File: COPYING.LESSER
Requires-Dist: kisstdlib==0.0.11
